pylid2/__init__.py
pylid2/wrapper.py
pylid2/bindings/__init__.py
pylid2/bindings/fn_types.py
pylid2/bindings/lsd_ctypes.py
pylid2/lib/linux/libEDLines.so
pylid2/lib/linux/liblsd.so
pylid2-0.0.5.dist-info/LICENSE
pylid2-0.0.5.dist-info/METADATA
pylid2-0.0.5.dist-info/WHEEL
pylid2-0.0.5.dist-info/top_level.txt
pylid2-0.0.5.dist-info/RECORD
