Metadata-Version: 2.1
Name: pylid2
Version: 0.0.5
Summary: pylisd is line 
Home-page: UNKNOWN
Author: Gefu Tang, anyongjin
Author-email: a@163.com
License: BSD
Keywords: LSD
Platform: UNKNOWN
License-File: LICENSE
